cryptofield
