Metadata-Version: 1.1
Name: django-cryptofield
Version: 0.1
Summary: A field for database backed password crypto
Home-page: http://github.com/fmorgner/django_cryptofield
Author: Felix Morgner
Author-email: felix.morgner@gmail.com
License: BSD
Keywords: django crypto pgcrypto
Platform: UNKNOWN
Classifier: Programming Language :: Python
Classifier: Programming Language :: Python :: 3
Classifier: License :: OSI Approved :: BSD License
Classifier: Operating System :: OS Independent
Classifier: Framework :: Django
